mlperf_loadgen.cpython-37m-x86_64-linux-gnu.so
mlperf_loadgen_cb-1.1.0.dist-info/METADATA
mlperf_loadgen_cb-1.1.0.dist-info/WHEEL
mlperf_loadgen_cb-1.1.0.dist-info/top_level.txt
mlperf_loadgen_cb-1.1.0.dist-info/RECORD
