Metadata-Version: 2.1
Name: mlperf-loadgen-cb
Version: 1.1.0
Summary: MLPerf Inference LoadGen python bindings
Home-page: https://github.com/xy223/inference
Author: Rachel Yong
Author-email: Graberial@outlook.com
License: Apache License
Platform: UNKNOWN
